pypomes_store/__init__.py
pypomes_store/minio_client.py
pypomes_store/minio_pomes.py
pypomes_store-0.2.7.dist-info/METADATA
pypomes_store-0.2.7.dist-info/WHEEL
pypomes_store-0.2.7.dist-info/licenses/LICENSE
pypomes_store-0.2.7.dist-info/RECORD
