Metadata-Version: 2.3
Name: pypomes_store
Version: 0.2.7
Summary: A collection of Python pomes, pennyeach (object storage modules)
Project-URL: Homepage, https://github.com/TheWiseCoder/PyPomes-Store
Project-URL: Bug Tracker, https://github.com/TheWiseCoder/PyPomes-Store/issues
Author-email: GT Nunes <wisecoder01@gmail.com>
License-File: LICENSE
Classifier: License :: OSI Approved :: MIT License
Classifier: Operating System :: OS Independent
Classifier: Programming Language :: Python :: 3
Requires-Python: >=3.10
Requires-Dist: minio>=7.2.5
Requires-Dist: pip>=24.0
Requires-Dist: pypomes-core>=0.8.8
Requires-Dist: setuptools>=68.0.0
Requires-Dist: unidecode>=1.3.6
Requires-Dist: wheel>=0.42.0
